AUTHORS
COPYING
ChangeLog
ChangeLog.in
MANIFEST
MANIFEST.in
NEWS
README
TODO
setup.cfg
setup.py
bin/mminfo
contrib/eyeD3-frames-patch.diff
doc/Makefile
doc/conf.py
doc/index.rst
doc/parser.rst
doc/usage.rst
doc/.build/doctrees/environment.pickle
doc/.build/doctrees/index.doctree
doc/.build/doctrees/parser.doctree
doc/.build/doctrees/usage.doctree
doc/html/.buildinfo
doc/html/genindex.html
doc/html/index.html
doc/html/objects.inv
doc/html/parser.html
doc/html/search.html
doc/html/searchindex.js
doc/html/usage.html
doc/html/_sources/index.txt
doc/html/_sources/parser.txt
doc/html/_sources/usage.txt
doc/html/_static/basic.css
doc/html/_static/default.css
doc/html/_static/doctools.js
doc/html/_static/file.png
doc/html/_static/jquery.js
doc/html/_static/minus.png
doc/html/_static/plus.png
doc/html/_static/pygments.css
doc/html/_static/searchtools.js
doc/html/_static/sidebar.js
doc/html/_static/underscore.js
kaa_metadata.egg-info/PKG-INFO
kaa_metadata.egg-info/SOURCES.txt
kaa_metadata.egg-info/dependency_links.txt
kaa_metadata.egg-info/namespace_packages.txt
kaa_metadata.egg-info/not-zip-safe
kaa_metadata.egg-info/requires.txt
kaa_metadata.egg-info/top_level.txt
src/__init__.py
src/core.py
src/factory.py
src/fourcc.py
src/language.py
src/version.py
src/audio/ID3.py
src/audio/__init__.py
src/audio/ac3.py
src/audio/adts.py
src/audio/core.py
src/audio/flac.py
src/audio/m4a.py
src/audio/mp3.py
src/audio/ogg.py
src/audio/pcm.py
src/audio/webradio.py
src/audio/eyeD3/__init__.py
src/audio/eyeD3/binfuncs.py
src/audio/eyeD3/frames.py
src/audio/eyeD3/mp3.py
src/audio/eyeD3/tag.py
src/audio/eyeD3/utils.py
src/disc/CDDB.py
src/disc/__init__.py
src/disc/audio.py
src/disc/cdrom.py
src/disc/cdrommodule.c
src/disc/core.py
src/disc/data.py
src/disc/dvd.py
src/disc/ifomodule.c
src/disc/vcd.py
src/games/__init__.py
src/games/core.py
src/games/gameboy.py
src/games/snes.py
src/image/EXIF.py
src/image/IPTC.py
src/image/__init__.py
src/image/bmp.py
src/image/core.py
src/image/exiv2.cpp
src/image/generic.py
src/image/gif.py
src/image/jpg.py
src/image/png.py
src/image/tiff.py
src/misc/__init__.py
src/misc/directory.py
src/misc/xmlfile.py
src/video/__init__.py
src/video/asf.py
src/video/core.py
src/video/flv.py
src/video/mkv.py
src/video/mp4.py
