Metadata-Version: 1.0
Name: kaa-metadata
Version: 0.7.8dev-r4569-20111003
Summary: Module for retrieving information about media files
Home-page: http://freevo.org/kaa/
Author: Thomas Schueppel, Dirk Meyer, Jason Tackaberry
Author-email: freevo-devel@lists.sourceforge.net
License: GPL
Platform: UNKNOWN
